[
    {
        "q": "What percentage of their missiles did US President Donald Trump state Tehran still has access to?",
        "a": "21%-22%",
        "options": [
            "15%-16%",
            "21%-22%",
            "25%-26%",
            "30%-31%",
            "18%-19%"
        ],
        "cat": "Amount"
    },
    {
        "q": "How many days was the ceasefire between the US and Iran tentatively agreed to be extended for a new round of talks?",
        "a": "60 days",
        "options": [
            "30 days",
            "45 days",
            "60 days",
            "90 days",
            "120 days"
        ],
        "cat": "Amount"
    },
    {
        "q": "How many lives were claimed by Tehran's drone attack on Kuwait's main airport?",
        "a": "One life",
        "options": [
            "Zero lives",
            "One life",
            "Two lives",
            "Three lives",
            "Several lives"
        ],
        "cat": "Amount"
    },
    {
        "q": "What was the net foreign debt inflow for India in the April-June quarter, according to JM Financial Institutional Securities data?",
        "a": "$0.5 million",
        "options": [
            "$0.1 million",
            "$0.5 million",
            "$1.0 million",
            "$1.5 million",
            "$2.0 million"
        ],
        "cat": "Amount"
    },
    {
        "q": "What was the aggregate investment limit fixed for government bonds for April-September 2026 under the revised RBI framework?",
        "a": "\u20b94.62 trillion",
        "options": [
            "\u20b94.50 trillion",
            "\u20b94.62 trillion",
            "\u20b94.70 trillion",
            "\u20b94.77 trillion",
            "\u20b94.80 trillion"
        ],
        "cat": "Amount"
    },
    {
        "q": "What is the aggregate investment limit for state bonds set for October 2026-March 2027 under the revised RBI framework?",
        "a": "\u20b91.64 trillion",
        "options": [
            "\u20b91.50 trillion",
            "\u20b91.53 trillion",
            "\u20b91.60 trillion",
            "\u20b91.64 trillion",
            "\u20b91.70 trillion"
        ],
        "cat": "Amount"
    },
    {
        "q": "What was the opening yield on the 10-year benchmark government bond on Friday?",
        "a": "6.99%",
        "options": [
            "6.90%",
            "6.95%",
            "6.99%",
            "7.01%",
            "7.05%"
        ],
        "cat": "Amount"
    },
    {
        "q": "What was the NRI ownership as a percentage of Sensex market capitalization as of the quarter ending March 2026?",
        "a": "0.7%",
        "options": [
            "0.5%",
            "0.7%",
            "1.0%",
            "1.2%",
            "1.5%"
        ],
        "cat": "Amount"
    },
    {
        "q": "What was the total worth of shares pulled out by FPIs from India's secondary market since 2025?",
        "a": "$57.68 billion",
        "options": [
            "$50.00 billion",
            "$55.00 billion",
            "$57.68 billion",
            "$60.00 billion",
            "$62.50 billion"
        ],
        "cat": "Amount"
    },
    {
        "q": "By what percentage had Brent crude rallied since the West Asia conflict began on 28 February?",
        "a": "31%",
        "options": [
            "25%",
            "28%",
            "31%",
            "34%",
            "37%"
        ],
        "cat": "Amount"
    },
    {
        "q": "What was India's GDP growth estimated at for the overall financial year 2025-26?",
        "a": "7.7%",
        "options": [
            "7.0%",
            "7.1%",
            "7.5%",
            "7.7%",
            "7.8%"
        ],
        "cat": "Amount"
    },
    {
        "q": "What is the policy Repo Rate maintained by the Monetary Policy Committee (MPC)?",
        "a": "5.25%",
        "options": [
            "4.75%",
            "5.00%",
            "5.25%",
            "5.50%",
            "5.75%"
        ],
        "cat": "Amount"
    },
    {
        "q": "What is the projected inflation number for FY27, increased by the MPC?",
        "a": "5.1%",
        "options": [
            "4.5%",
            "4.8%",
            "5.1%",
            "5.4%",
            "5.7%"
        ],
        "cat": "Amount"
    },
    {
        "q": "What is the proposed initial public offering (IPO) amount for Truhome Finance Limited?",
        "a": "\u20b93,000 crore",
        "options": [
            "\u20b92,500 crore",
            "\u20b92,800 crore",
            "\u20b93,000 crore",
            "\u20b93,200 crore",
            "\u20b93,500 crore"
        ],
        "cat": "Amount"
    },
    {
        "q": "What was the growth rate of private final consumption expenditure (PFCE) estimated for 2025-26?",
        "a": "7.7%",
        "options": [
            "6.5%",
            "7.0%",
            "7.2%",
            "7.7%",
            "8.0%"
        ],
        "cat": "Amount"
    },
    {
        "q": "What was the capital gains tax rate on shares worth over \u20b91 lakh if sold after one year?",
        "a": "12.5%",
        "options": [
            "10%",
            "12.5%",
            "15%",
            "17.5%",
            "20%"
        ],
        "cat": "Amount"
    },
    {
        "q": "The RBI lowered its real GDP growth expectations for 2026-27 to what percentage?",
        "a": "6.6%",
        "options": [
            "6.0%",
            "6.3%",
            "6.6%",
            "6.9%",
            "7.0%"
        ],
        "cat": "Amount"
    },
    {
        "q": "What was the Sensex decline in points on Friday?",
        "a": "116.67 points",
        "options": [
            "100.00 points",
            "110.50 points",
            "116.67 points",
            "120.25 points",
            "130.00 points"
        ],
        "cat": "Amount"
    },
    {
        "q": "What was the percentage fall in the Kospi index in Asian markets on Friday?",
        "a": "5.5%",
        "options": [
            "4.0%",
            "4.5%",
            "5.0%",
            "5.5%",
            "6.0%"
        ],
        "cat": "Amount"
    },
    {
        "q": "What is the current Securities Transaction Tax (STT) levied on equity cash?",
        "a": "0.1%",
        "options": [
            "0.05%",
            "0.1%",
            "0.15%",
            "0.2%",
            "0.25%"
        ],
        "cat": "Amount"
    },
    {
        "q": "Which US President claimed that 'final negotiations' to end the war with Iran were in process?",
        "a": "Donald Trump",
        "options": [
            "Joe Biden",
            "Barack Obama",
            "Donald Trump",
            "George W. Bush",
            "Bill Clinton"
        ],
        "cat": "Who"
    },
    {
        "q": "Who is the current Foreign Minister of Iran mentioned in the news text?",
        "a": "Abbas Araghchi",
        "options": [
            "Mohammad Javad Zarif",
            "Abbas Araghchi",
            "Hossein Amir-Abdollahian",
            "Ali Akbar Salehi",
            "Manouchehr Mottaki"
        ],
        "cat": "Who"
    },
    {
        "q": "Who is the military adviser to Iran's Supreme Leader Ayatollah Mojtaba Khamenei, quoted in an interview with CNN?",
        "a": "Mohsen Rezaei",
        "options": [
            "Mohsen Rezaei",
            "Ali Shamkhani",
            "Ali Larijani",
            "Saeed Jalili",
            "Gholam-Ali Haddad-Adel"
        ],
        "cat": "Who"
    },
    {
        "q": "Who is the US State Department spokesperson mentioned in the news?",
        "a": "Tommy Pigott",
        "options": [
            "Ned Price",
            "Matthew Miller",
            "Tommy Pigott",
            "Jen Psaki",
            "Heather Nauert"
        ],
        "cat": "Who"
    },
    {
        "q": "Which entity introduced the Fully Accessible Route (FAR) in 2020 to facilitate greater foreign participation in India\u2019s sovereign debt market?",
        "a": "Reserve Bank of India (RBI)",
        "options": [
            "SEBI",
            "Ministry of Finance",
            "NITI Aayog",
            "Reserve Bank of India (RBI)",
            "NABARD"
        ],
        "cat": "Who"
    },
    {
        "q": "Who is the treasury head at Ujjivan Small Finance Bank, quoted regarding the 10-year bond yield?",
        "a": "Rajeev Pawar",
        "options": [
            "V.R.C. Reddy",
            "Rajeev Pawar",
            "Vijay Kuppa",
            "Nilesh Shah",
            "Chirag Shah"
        ],
        "cat": "Who"
    },
    {
        "q": "Who is the Chief Economic Advisor who stated that RBI's assessment of GDP and inflation 'seem fair estimates'?",
        "a": "V. Anantha Nageswaran",
        "options": [
            "Raghuram Rajan",
            "Urjit Patel",
            "V. Anantha Nageswaran",
            "Arvind Subramanian",
            "K.V. Subramanian"
        ],
        "cat": "Who"
    },
    {
        "q": "Who acquired Truhome Finance Limited (formerly Shriram Housing Finance Limited) in December 2024?",
        "a": "Warburg Pincus",
        "options": [
            "Blackstone",
            "KKR",
            "The Carlyle Group",
            "Warburg Pincus",
            "Apollo Global Management"
        ],
        "cat": "Who"
    },
    {
        "q": "Who was the Finance Minister who reintroduced LTCG at 10% in 2018?",
        "a": "Arun Jaitley",
        "options": [
            "P. Chidambaram",
            "Arun Jaitley",
            "Nirmala Sitharaman",
            "Manmohan Singh",
            "Yashwant Sinha"
        ],
        "cat": "Who"
    },
    {
        "q": "Who is the current Reserve Bank of India (RBI) Governor mentioned in the news?",
        "a": "Sanjay Malhotra",
        "options": [
            "Shaktikanta Das",
            "Urjit Patel",
            "Raghuram Rajan",
            "D. Subbarao",
            "Sanjay Malhotra"
        ],
        "cat": "Who"
    },
    {
        "q": "Towards which strait did the US military say Iranian drones were launched?",
        "a": "Strait of Hormuz",
        "options": [
            "Strait of Gibraltar",
            "Strait of Malacca",
            "Strait of Hormuz",
            "Bab-el-Mandeb Strait",
            "Dardanelles Strait"
        ],
        "cat": "Where"
    },
    {
        "q": "Where were two of Islamic Republic's coastal surveillance radar sites struck in retaliation by US Central Command?",
        "a": "Goruk and on Qeshm Island",
        "options": [
            "Tehran and Isfahan",
            "Shiraz and Tabriz",
            "Mashhad and Ahvaz",
            "Goruk and on Qeshm Island",
            "Kish Island and Kharg Island"
        ],
        "cat": "Where"
    },
    {
        "q": "Which country's main airport was attacked by a drone, claiming one life?",
        "a": "Kuwait",
        "options": [
            "Saudi Arabia",
            "Qatar",
            "UAE",
            "Kuwait",
            "Oman"
        ],
        "cat": "Where"
    },
    {
        "q": "Where did US President Donald Trump make his statement regarding the situation with Iran going 'quite well' on Friday?",
        "a": "Wisconsin",
        "options": [
            "Washington D.C.",
            "New York",
            "Florida",
            "California",
            "Wisconsin"
        ],
        "cat": "Where"
    },
    {
        "q": "The US Central Command rejected claims that Iran struck which US 5th fleet headquarters?",
        "a": "Bahrain",
        "options": [
            "Qatar",
            "UAE",
            "Oman",
            "Bahrain",
            "Saudi Arabia"
        ],
        "cat": "Where"
    },
    {
        "q": "Which country's President did Iran's Foreign Minister Abbas Araghchi appeal to save their country from its 'real foe'?",
        "a": "Lebanon",
        "options": [
            "Syria",
            "Iraq",
            "Yemen",
            "Lebanon",
            "Jordan"
        ],
        "cat": "Where"
    },
    {
        "q": "Where did US forces board a sanctioned oil tanker linked to Iran, as Washington seeks to prevent Iran from profiting off its oil?",
        "a": "Indian Ocean",
        "options": [
            "Persian Gulf",
            "Arabian Sea",
            "Red Sea",
            "Mediterranean Sea",
            "Indian Ocean"
        ],
        "cat": "Where"
    },
    {
        "q": "The Reserve Bank of India (RBI) is primarily located in which Indian city?",
        "a": "Mumbai",
        "options": [
            "New Delhi",
            "Bengaluru",
            "Chennai",
            "Kolkata",
            "Mumbai"
        ],
        "cat": "Where"
    },
    {
        "q": "Truhome Finance Limited is a wholly owned subsidiary of Shriram Finance Limited, which was acquired by New York-based global private equity firm. Which firm is this?",
        "a": "Warburg Pincus",
        "options": [
            "Blackstone",
            "The Carlyle Group",
            "Warburg Pincus",
            "Kohlberg Kravis Roberts",
            "Apollo Global Management"
        ],
        "cat": "Where"
    },
    {
        "q": "The Indian Institute of Journalism and New Media, where Subhana Shaikh completed her postgraduate diploma, is located in which city?",
        "a": "Bengaluru",
        "options": [
            "Mumbai",
            "New Delhi",
            "Chennai",
            "Kolkata",
            "Bengaluru"
        ],
        "cat": "Where"
    },
    {
        "q": "On what date did the three-month-old war between the US and Iran begin?",
        "a": "28 February 2026",
        "options": [
            "28 December 2025",
            "28 January 2026",
            "28 February 2026",
            "28 March 2026",
            "28 April 2026"
        ],
        "cat": "When"
    },
    {
        "q": "In which year was the Fully Accessible Route (FAR) framework introduced by the RBI?",
        "a": "2020",
        "options": [
            "2018",
            "2019",
            "2020",
            "2021",
            "2022"
        ],
        "cat": "When"
    },
    {
        "q": "For which period has the aggregate investment limit for government bonds been fixed at \u20b94.77 trillion?",
        "a": "October 2026-March 2027",
        "options": [
            "April-September 2026",
            "October 2026-March 2027",
            "April-September 2027",
            "October 2027-March 2028",
            "January-June 2026"
        ],
        "cat": "When"
    },
    {
        "q": "What was the fiscal year in which India's GDP grew at 7.1%?",
        "a": "2024-25",
        "options": [
            "2022-23",
            "2023-24",
            "2024-25",
            "2025-26",
            "2026-27"
        ],
        "cat": "When"
    },
    {
        "q": "The government updated the base year of the GDP data to which fiscal year earlier this year?",
        "a": "2022-23",
        "options": [
            "2020-21",
            "2021-22",
            "2022-23",
            "2023-24",
            "2024-25"
        ],
        "cat": "When"
    },
    {
        "q": "In which year was Long Term Capital Gains (LTCG) tax replaced with a securities transaction tax of 0.15% by then finance minister P. Chidambaram?",
        "a": "2004",
        "options": [
            "2002",
            "2004",
            "2006",
            "2008",
            "2010"
        ],
        "cat": "When"
    },
    {
        "q": "In which month and year was Truhome Finance Limited acquired by Warburg Pincus?",
        "a": "December 2024",
        "options": [
            "October 2024",
            "November 2024",
            "December 2024",
            "January 2025",
            "February 2025"
        ],
        "cat": "When"
    },
    {
        "q": "Until what date will the RBI bear hedging costs on fresh three-to five-year FCNR(B) deposits to attract dollar inflows?",
        "a": "September 30",
        "options": [
            "June 30",
            "July 30",
            "August 30",
            "September 30",
            "October 30"
        ],
        "cat": "When"
    },
    {
        "q": "On which date did the RBI Governor Sanjay Malhotra make the statement regarding India's strong economic condition post-MPC meeting?",
        "a": "June 5, 2026",
        "options": [
            "May 1, 2026",
            "May 15, 2026",
            "June 1, 2026",
            "June 5, 2026",
            "June 10, 2026"
        ],
        "cat": "When"
    },
    {
        "q": "In which fiscal year did the manufacturing sector grow at 10.7% as per the provisional estimates?",
        "a": "2025-26",
        "options": [
            "2023-24",
            "2024-25",
            "2025-26",
            "2026-27",
            "2022-23"
        ],
        "cat": "When"
    },
    {
        "q": "Why did the US military state it struck two of Islamic Republic's coastal surveillance radar sites?",
        "a": "To defend against further attacks",
        "options": [
            "To gather intelligence",
            "To disrupt communications",
            "To eliminate military personnel",
            "To defend against further attacks",
            "To provoke a wider conflict"
        ],
        "cat": "Why"
    },
    {
        "q": "What was Iran's clear demand in the peace proposal for resolving the parallel conflict in Lebanon?",
        "a": "Ceasefire between Israel and Hezbollah",
        "options": [
            "Withdrawal of US troops",
            "End of sanctions",
            "Ceasefire between Israel and Hezbollah",
            "Financial aid to Lebanon",
            "Recognition of Iranian influence"
        ],
        "cat": "Why"
    },
    {
        "q": "What was the primary purpose of the US Department of the Treasury's OFAC targeting an Iranian LPG smuggling network?",
        "a": "To prevent Iran from profiting off its oil and other goods",
        "options": [
            "To reduce global gas prices",
            "To investigate environmental violations",
            "To prevent Iran from profiting off its oil and other goods",
            "To support regional maritime trade",
            "To impose travel bans on individuals"
        ],
        "cat": "Why"
    },
    {
        "q": "What is the overarching goal of the US maintaining 'maximum pressure' on the Iranian regime, as stated by Tommy Pigott?",
        "a": "Through Economic Fury",
        "options": [
            "To initiate diplomatic talks",
            "To encourage regime change",
            "Through Economic Fury",
            "To provide humanitarian aid",
            "To promote regional stability"
        ],
        "cat": "Why"
    },
    {
        "q": "What was the main objective behind the RBI easing investment restrictions and expanding the pool of securities under the Fully Accessible Route (FAR)?",
        "a": "To revive overseas debt inflows",
        "options": [
            "To increase domestic liquidity",
            "To control inflation",
            "To revive overseas debt inflows",
            "To strengthen the banking sector",
            "To reduce government expenditure"
        ],
        "cat": "Why"
    },
    {
        "q": "What was one of the reasons cited for the slowdown in foreign investment in Indian debt?",
        "a": "Narrowing interest-rate differential with the US",
        "options": [
            "High domestic interest rates",
            "Stronger rupee",
            "Narrowing interest-rate differential with the US",
            "Increased government borrowing",
            "Political stability in the region"
        ],
        "cat": "Why"
    },
    {
        "q": "Why were the RBI's measures to attract foreign capital from NRIs and OCIs expected to succeed materially if complemented by other measures?",
        "a": "To increase the ease of doing business",
        "options": [
            "To boost domestic consumption",
            "To increase export competitiveness",
            "To lower corporate taxes",
            "To increase the ease of doing business",
            "To reduce unemployment rates"
        ],
        "cat": "Why"
    },
    {
        "q": "What was the reason for the RBI's MPC reducing the growth forecast for FY27 and increasing the inflation number?",
        "a": "Passthrough of higher fuel prices visible in overall price rise",
        "options": [
            "Stronger economic outlook",
            "Lower global crude prices",
            "Passthrough of higher fuel prices visible in overall price rise",
            "Increased government spending",
            "Reduced foreign investment"
        ],
        "cat": "Why"
    },
    {
        "q": "What is the primary purpose for which Truhome Finance Limited proposes to utilize the net proceeds from its IPO?",
        "a": "Augmenting the capital base to meet future capital requirements",
        "options": [
            "To expand into international markets",
            "To acquire smaller housing finance companies",
            "To pay off existing debts",
            "Augmenting the capital base to meet future capital requirements",
            "To invest in new technology ventures"
        ]
    },
    {
        "q": "Why did benchmark indices Sensex and Nifty end lower on Friday?",
        "a": "Profit-taking after RBI lowered growth expectations and forecast inflation to rise",
        "options": [
            "Strong global market performance",
            "Unexpected policy rate hike",
            "Profit-taking after RBI lowered growth expectations and forecast inflation to rise",
            "Increased foreign institutional investment",
            "Positive economic growth data"
        ],
        "cat": "Why"
    },
    {
        "q": "According to RBI Governor Sanjay Malhotra, what worries the RBI the most regarding the West Asia conflict?",
        "a": "The duration of the conflict and the time it would take for the restoration of the supply chain",
        "options": [
            "The immediate impact on crude oil prices",
            "The duration of the conflict and the time it would take for the restoration of the supply chain",
            "The potential for a regional war",
            "The decline in foreign exchange reserves",
            "The increase in domestic inflation due to food prices"
        ],
        "cat": "Why"
    },
    {
        "q": "Why did the RBI remove the requirement for foreign investors to comply with short-term investment limits, security-wise limits, and concentration limits under the general route?",
        "a": "To dismantle longstanding restrictions governing FPI investments",
        "options": [
            "To encourage domestic retail investment",
            "To simplify tax regulations for FPIs",
            "To dismantle longstanding restrictions governing FPI investments",
            "To reduce the volatility in the bond market",
            "To limit speculative trading by foreign entities"
        ],
        "cat": "Why"
    },
    {
        "q": "What was the objective of the RBI merging the separate \u2018general\u2019 and \u2018long-term\u2019 investment categories into a single limit for government bonds and state bonds?",
        "a": "To simplify the investment limit structure",
        "options": [
            "To increase the total investment capacity for FPIs",
            "To reduce administrative burden for domestic banks",
            "To simplify the investment limit structure",
            "To align with international accounting standards",
            "To prevent capital flight from the country"
        ],
        "cat": "Why"
    },
    {
        "q": "What was the primary reason for the US military boarding a sanctioned oil tanker linked to Iran in the Indian Ocean?",
        "a": "To prevent Iran from profiting off its oil and other goods",
        "options": [
            "To conduct a safety inspection",
            "To search for illegal weapons",
            "To prevent Iran from profiting off its oil and other goods",
            "To rescue distressed mariners",
            "To enforce international maritime law"
        ],
        "cat": "Why"
    },
    {
        "q": "Why did Prime Minister Narendra Modi post on X following the GDP data release?",
        "a": "To reflect the inherent strength of the economy and success of reforms",
        "options": [
            "To announce new economic policies",
            "To caution about global uncertainties",
            "To reflect the inherent strength of the economy and success of reforms",
            "To criticize opposition economic policies",
            "To solicit public feedback on economic growth"
        ],
        "cat": "Why"
    },
    {
        "q": "Why did the government scrap taxes on interest income and capital gains for eligible foreign investors in government securities from April 1, 2026?",
        "a": "To support the rupee and attract foreign capital",
        "options": [
            "To reduce the national debt",
            "To simplify the tax code",
            "To support the rupee and attract foreign capital",
            "To encourage domestic investment",
            "To comply with international trade agreements"
        ],
        "cat": "Why"
    }
]